facebook_crawler.py
develop/__init__.py
develop/fanspage.py
facebook_crawler-0.0.28.dist-info/LICENSE
facebook_crawler-0.0.28.dist-info/METADATA
facebook_crawler-0.0.28.dist-info/WHEEL
facebook_crawler-0.0.28.dist-info/top_level.txt
facebook_crawler-0.0.28.dist-info/RECORD
