Metadata-Version: 2.1
Name: facebook-crawler
Version: 0.0.28
Summary: Facebook crawler package can help you crawl the posts on public fanspages and groups from Facebook.
Home-page: https://github.com/TLYu0419/facebook_crawler
Author: TENG-LIN YU
Author-email: tlyu0419@gmail.com
License: UNKNOWN
Platform: UNKNOWN
Classifier: Programming Language :: Python :: 3
Classifier: License :: OSI Approved :: Apache Software License
Classifier: Operating System :: OS Independent
Requires-Python: >=3.6
Requires-Dist: bs4
Requires-Dist: lxml
Requires-Dist: numpy
Requires-Dist: pandas
Requires-Dist: requests
